Metadata-Version: 2.1
Name: medicc2
Version: 1.1.1
Summary: Whole-genome doubling-aware copy number phylogenies for cancer evolution
Home-page: https://bitbucket.org/schwarzlab/medicc2
Author: Tom L Kaufmann, Marina Petkovic, Roland F Schwarz
Author-email: tkau93@gmail.com, marina.55kovic@gmail.com, roland.f.schwarz@gmail.com
License: GPL-3
Classifier: Programming Language :: Python :: 3
Classifier: License :: OSI Approved :: MIT License
Classifier: Operating System :: OS Independent
License-File: LICENSE
Requires-Dist: numpy<2.0,>=1.20.1
Requires-Dist: pyyaml>=5.4.1
Requires-Dist: pandas<2.1,>=1.2
Requires-Dist: biopython>=1.78
Requires-Dist: scipy>=1.7
Requires-Dist: matplotlib>=3.3.4
Provides-Extra: parallelization
Requires-Dist: joblib>=1.0.1; extra == "parallelization"
